linesman/__init__.py
linesman/geo.py
linesman/geometry.py
linesman/measure.py
linesman/output.py
linesman/parse.py
gpx_linesman-0.3.0.dist-info/entry_points.txt
gpx_linesman-0.3.0.dist-info/LICENSE
gpx_linesman-0.3.0.dist-info/WHEEL
gpx_linesman-0.3.0.dist-info/METADATA
gpx_linesman-0.3.0.dist-info/RECORD
