Metadata-Version: 2.1
Name: gpx-linesman
Version: 0.3.0
Summary: Command line tool for measuring the straightness of a gpx track
Home-page: https://github.com/burrscurr/linesman.git
License: MIT
Author: burrscurr
Author-email: burrscurr@users.noreply.github.com
Requires-Python: >=3.6,<4.0
Classifier: Environment :: Console
Classifier: License :: OSI Approved :: MIT License
Classifier: Operating System :: OS Independent
Classifier: Programming Language :: Python :: 3
Classifier: Programming Language :: Python :: 3.6
Classifier: Programming Language :: Python :: 3.7
Classifier: Programming Language :: Python :: 3.8
Classifier: Programming Language :: Python :: 3.9
Classifier: Topic :: Scientific/Engineering :: GIS
Requires-Dist: geographiclib (>=1.50,<2.0)
Requires-Dist: gpxpy (>=1.4.2,<2.0.0)
Requires-Dist: importlib-metadata (>=1.0,<2.0); python_version < "3.8"
Requires-Dist: pyproj (>=3.0.0,<4.0.0)
Project-URL: Documentation, https://linesman.readthedocs.io
Project-URL: Repository, https://github.com/burrscurr/linesman.git
